pyrtcm/__init__.py
pyrtcm/_version.py
pyrtcm/exceptions.py
pyrtcm/rtcmhelpers.py
pyrtcm/rtcmmessage.py
pyrtcm/rtcmreader.py
pyrtcm/rtcmtables.py
pyrtcm/rtcmtypes_core.py
pyrtcm/rtcmtypes_get.py
pyrtcm/rtcmtypes_get_igs.py
pyrtcm/rtcmtypes_get_msm.py
pyrtcm/socketwrapper.py
pyrtcm-1.1.7.dist-info/licenses/LICENSE
pyrtcm-1.1.7.dist-info/METADATA
pyrtcm-1.1.7.dist-info/WHEEL
pyrtcm-1.1.7.dist-info/top_level.txt
pyrtcm-1.1.7.dist-info/RECORD
