Metadata-Version: 2.4
Name: pyrtcm
Version: 1.1.7
Summary: RTCM3 protocol parser
Author-email: semuadmin <semuadmin@semuconsulting.com>
Maintainer-email: semuadmin <semuadmin@semuconsulting.com>
License: BSD 3-Clause License ("BSD License 2.0", "Revised BSD License", "New BSD License", or "Modified BSD License")
Project-URL: homepage, https://github.com/semuconsulting/pyrtcm
Project-URL: documentation, https://www.semuconsulting.com/pyrtcm/
Project-URL: repository, https://github.com/semuconsulting/pyrtcm
Project-URL: changelog, https://github.com/semuconsulting/pyrtcm/blob/master/RELEASE_NOTES.md
Classifier: Operating System :: OS Independent
Classifier: Development Status :: 5 - Production/Stable
Classifier: Environment :: MacOS X
Classifier: Environment :: Win32 (MS Windows)
Classifier: Environment :: X11 Applications
Classifier: Environment :: Console
Classifier: Intended Audience :: Developers
Classifier: Intended Audience :: Science/Research
Classifier: Intended Audience :: End Users/Desktop
Classifier: Programming Language :: Python :: 3
Classifier: Programming Language :: Python :: 3.9
Classifier: Programming Language :: Python :: 3.10
Classifier: Programming Language :: Python :: 3.11
Classifier: Programming Language :: Python :: 3.12
Classifier: Programming Language :: Python :: 3.13
Classifier: License :: OSI Approved :: BSD License
Classifier: Topic :: Utilities
Classifier: Topic :: Software Development :: Libraries :: Python Modules
Classifier: Topic :: Scientific/Engineering :: GIS
Requires-Python: >=3.9
License-File: LICENSE
Provides-Extra: deploy
Requires-Dist: build; extra == "deploy"
Requires-Dist: pip; extra == "deploy"
Requires-Dist: setuptools>=75.0; extra == "deploy"
Requires-Dist: wheel; extra == "deploy"
Provides-Extra: test
Requires-Dist: bandit; extra == "test"
Requires-Dist: black; extra == "test"
Requires-Dist: pylint; extra == "test"
Requires-Dist: pytest; extra == "test"
Requires-Dist: pytest-cov; extra == "test"
Requires-Dist: Sphinx; extra == "test"
Requires-Dist: sphinx-rtd-theme; extra == "test"
Dynamic: license-file
